Content/Activities_verylow.gif
Content/CalibFile.png
Content/Calib_ext.png
Content/Calib_int.png
Content/FilterPlot.png
Content/OpenSim.JPG
Content/OpenSim_logs.png
Content/P2S_calibration.png
Content/P2S_filtering.png
Content/P2S_kinematics.png
Content/P2S_markeraugmentation.png
Content/P2S_personassociation.png
Content/P2S_poseestimation.png
Content/P2S_synchronization.png
Content/P2S_triangulation.png
Content/Pose2D.png
Content/Pose2Sim Blender.mp4
Content/Pose2Sim_workflow.jpg
Content/Pose2Sim_workflow_utilities.jpg
Content/Storage.png
Content/checkerboard.jpg
Content/paper.bib
Content/paper.md
Content/synchro.jpg
Content/synchro_multi.jpg
Content/website/index.md
Pose2Sim/Pose2Sim.py
Pose2Sim/__init__.py
Pose2Sim/calibration.py
Pose2Sim/common.py
Pose2Sim/filtering.py
Pose2Sim/kinematics.py
Pose2Sim/markerAugmentation.py
Pose2Sim/personAssociation.py
Pose2Sim/poseEstimation.py
Pose2Sim/skeletons.py
Pose2Sim/synchronization.py
Pose2Sim/triangulation.py
Pose2Sim/Demo_Batch/Config.toml
Pose2Sim/Demo_Batch/Trial_1/Config.toml
Pose2Sim/Demo_Batch/Trial_1/videos/cam01.mp4
Pose2Sim/Demo_Batch/Trial_1/videos/cam02.mp4
Pose2Sim/Demo_Batch/Trial_1/videos/cam03.mp4
Pose2Sim/Demo_Batch/Trial_1/videos/cam04.mp4
Pose2Sim/Demo_Batch/Trial_2/Config.toml
Pose2Sim/Demo_Batch/Trial_2/videos/cam01.mp4
Pose2Sim/Demo_Batch/Trial_2/videos/cam02.mp4
Pose2Sim/Demo_Batch/Trial_2/videos/cam03.mp4
Pose2Sim/Demo_Batch/Trial_2/videos/cam04.mp4
Pose2Sim/Demo_Batch/calibration/Calib.qca.txt
Pose2Sim/Demo_MultiPerson/Config.toml
Pose2Sim/Demo_MultiPerson/calibration/Calib.qca.txt
Pose2Sim/Demo_MultiPerson/videos/cam01.mp4
Pose2Sim/Demo_MultiPerson/videos/cam02.mp4
Pose2Sim/Demo_MultiPerson/videos/cam03.mp4
Pose2Sim/Demo_MultiPerson/videos/cam04.mp4
Pose2Sim/Demo_SinglePerson/Config.toml
Pose2Sim/Demo_SinglePerson/calibration/Calib.qca.txt
Pose2Sim/Demo_SinglePerson/calibration/Calib_scene.toml
Pose2Sim/Demo_SinglePerson/calibration/calib_cam01_ext.png
pose2sim-0.10.39.dist-info/licenses/LICENSE
pose2sim-0.10.39.dist-info/METADATA
pose2sim-0.10.39.dist-info/WHEEL
pose2sim-0.10.39.dist-info/entry_points.txt
pose2sim-0.10.39.dist-info/top_level.txt
pose2sim-0.10.39.dist-info/RECORD
