Metadata-Version: 2.4
Name: pose2sim
Version: 0.10.39
Summary: Markerless kinematics with any cameras — From 2D Pose estimation to 3D OpenSim motion
Author-email: David Pagnon <contact@david-pagnon.com>
Maintainer-email: David Pagnon <contact@david-pagnon.com>
License-Expression: BSD-3-Clause
Project-URL: Homepage, https://github.com/perfanalytics/pose2sim
Project-URL: Bug Tracker, https://github.com/perfanalytics/pose2sim/issues
Keywords: markerless,kinematics,OpenPose,OpenSim,3D human pose,biomechanics,mocap,blender,motion capture
Classifier: Programming Language :: Python :: 3
Classifier: Development Status :: 3 - Alpha
Classifier: Intended Audience :: Science/Research
Classifier: Intended Audience :: Healthcare Industry
Classifier: Intended Audience :: Education
Classifier: Operating System :: OS Independent
Classifier: Topic :: Scientific/Engineering
Classifier: Topic :: Scientific/Engineering :: Image Processing
Classifier: Topic :: Scientific/Engineering :: Medical Science Apps.
Classifier: Topic :: Multimedia :: Graphics
Classifier: Topic :: Multimedia :: Graphics :: 3D Modeling
Requires-Python: >=3.9
License-File: LICENSE
Requires-Dist: toml
Requires-Dist: numpy<2.0; python_version < "3.12"
Requires-Dist: numpy<2.3,>=2.0; python_version >= "3.12"
Requires-Dist: lxml
Requires-Dist: matplotlib
Requires-Dist: mpl_interactions
Requires-Dist: PyQt5
Requires-Dist: tqdm
Requires-Dist: anytree
Requires-Dist: pandas>=1.5
Requires-Dist: scipy
Requires-Dist: statsmodels
Requires-Dist: filterpy
Requires-Dist: ipython
Requires-Dist: c3d
Requires-Dist: rtmlib
Requires-Dist: openvino
Requires-Dist: onnxruntime
Requires-Dist: opencv-python!=4.11.*
Dynamic: license-file
